pytest_r_snapshot/__init__.py
pytest_r_snapshot/chunks.py
pytest_r_snapshot/errors.py
pytest_r_snapshot/normalize.py
pytest_r_snapshot/plugin.py
pytest_r_snapshot/runner.py
pytest_r_snapshot/settings.py
pytest_r_snapshot/snapshot.py
pytest_r_snapshot-0.1.1.dist-info/METADATA
pytest_r_snapshot-0.1.1.dist-info/WHEEL
pytest_r_snapshot-0.1.1.dist-info/entry_points.txt
pytest_r_snapshot-0.1.1.dist-info/licenses/LICENSE
pytest_r_snapshot-0.1.1.dist-info/RECORD
