Metadata-Version: 2.4
Name: pytest-r-snapshot
Version: 0.1.1
Summary: A pytest plugin for snapshot testing against R code outputs
Project-URL: Homepage, https://nanx.me/pytest-r-snapshot/
Project-URL: Documentation, https://nanx.me/pytest-r-snapshot/
Project-URL: Repository, https://github.com/nanxstats/pytest-r-snapshot
Project-URL: Issues, https://github.com/nanxstats/pytest-r-snapshot/issues
Project-URL: Changelog, https://github.com/nanxstats/pytest-r-snapshot/blob/main/CHANGELOG.md
Author-email: Nan Xiao <me@nanx.me>
License-File: LICENSE
Classifier: Development Status :: 3 - Alpha
Classifier: Intended Audience :: Developers
Classifier: License :: OSI Approved :: MIT License
Classifier: Programming Language :: Python :: 3
Classifier: Programming Language :: Python :: 3.10
Classifier: Programming Language :: Python :: 3.11
Classifier: Programming Language :: Python :: 3.12
Classifier: Programming Language :: Python :: 3.13
Classifier: Programming Language :: Python :: 3.14
Classifier: Topic :: Software Development :: Quality Assurance
Classifier: Topic :: Software Development :: Testing
Requires-Python: >=3.10
Requires-Dist: pytest>=7.0.0
